high_order_layers/FourierLayers.py
high_order_layers/Functions.py
high_order_layers/HighOrderConvolution2D.py
high_order_layers/HighOrderLayer.py
high_order_layers/PolynomialLayers.py
high_order_layers/__init__.py
high_order_layers-1.1.6.dist-info/LICENSE
high_order_layers-1.1.6.dist-info/METADATA
high_order_layers-1.1.6.dist-info/WHEEL
high_order_layers-1.1.6.dist-info/top_level.txt
high_order_layers-1.1.6.dist-info/RECORD
