Metadata-Version: 2.1
Name: high-order-layers
Version: 1.1.6
Summary: Polynomial, piecewise polynomial, fourier series layers for tensorflow
Home-page: https://github.com/jloveric/high-order-layers
Author: John Loverich
Author-email: john.loverich@gmail.com
License: UNKNOWN
Platform: UNKNOWN
Classifier: Programming Language :: Python :: 3
Classifier: License :: OSI Approved :: MIT License
Classifier: Operating System :: OS Independent
Requires-Dist: numpy
Requires-Dist: tensorflow
